rejax-0.1.2.dist-info/METADATA
rejax-0.1.2.dist-info/WHEEL
rejax-0.1.2.dist-info/entry_points.txt
rejax-0.1.2.dist-info/licenses/LICENSE
rejax/__init__.py
rejax/algos/__init__.py
rejax/algos/algorithm.py
rejax/algos/dqn.py
rejax/algos/iqn.py
rejax/algos/mixins.py
rejax/algos/ppo.py
rejax/algos/pqn.py
rejax/algos/sac.py
rejax/algos/td3.py
rejax/buffers.py
rejax/compat/__init__.py
rejax/compat/brax2gymnax.py
rejax/compat/gymnasium2gymnax.py
rejax/compat/jumanji2gymnax.py
rejax/compat/navix2gymnax.py
rejax/evaluate.py
rejax/networks.py
rejax/normalize.py
rejax-0.1.2.dist-info/RECORD
