Metadata-Version: 2.1
Name: rejax
Version: 0.1.2
Summary: Vectorizable RL algorithms in pure JAX
Author: Jarek Liesen
License: Apache-2.0
Requires-Python: >=3.10
Requires-Dist: pyyaml>=6.0.2
Requires-Dist: flax>=0.9.0
Requires-Dist: optax>=0.2.3
Requires-Dist: brax>=0.11.0
Requires-Dist: evosax>=0.1.6
Requires-Dist: distrax>=0.1.5
Requires-Dist: gymnax>=0.0.8
Requires-Dist: jax>=0.4.34
Provides-Extra: compat
Requires-Dist: brax>=0.11.0; extra == "compat"
Requires-Dist: craftax>=1.4.3; extra == "compat"
Requires-Dist: navix>=0.7.0; extra == "compat"
Requires-Dist: jumanji>=1.0.1; extra == "compat"
Requires-Dist: gymnasium>=1.0.0; extra == "compat"
